docs/_build/html/_modules/temoa/components/capacity.html
docs/_build/html/_modules/temoa/components/commodities.html
docs/_build/html/_modules/temoa/components/costs.html
docs/_build/html/_modules/temoa/components/limits.html
docs/_build/html/_modules/temoa/components/operations.html
docs/_build/html/_modules/temoa/components/reserves.html
docs/_build/html/_modules/temoa/components/storage.html
temoa/__about__.py
temoa/__init__.py
temoa/__main__.py
temoa/cli.py
temoa/py.typed
temoa/_internal/__init__.py
temoa/_internal/data_brick.py
temoa/_internal/exchange_tech_cost_ledger.py
temoa/_internal/run_actions.py
temoa/_internal/table_data_puller.py
temoa/_internal/table_writer.py
temoa/_internal/temoa_sequencer.py
temoa/components/capacity.py
temoa/components/commodities.py
temoa/components/costs.py
temoa/components/emissions.py
temoa/components/flows.py
temoa/components/geography.py
temoa/components/limits.py
temoa/components/operations.py
temoa/components/reserves.py
temoa/components/storage.py
temoa/components/technology.py
temoa/components/time.py
temoa/components/utils.py
temoa/core/__init__.py
temoa/core/config.py
temoa/core/model.py
temoa/core/modes.py
temoa/data_io/README.md
temoa/data_io/component_manifest.py
temoa/data_io/hybrid_loader.py
temoa/data_io/loader_manifest.py
temoa/data_processing/README.md
temoa/data_processing/__init__.py
temoa/data_processing/db_query.py
temoa/data_processing/db_to_excel.py
temoa/data_processing/make_output_plots.py
temoa/db_schema/temoa_schema_v3.sql
temoa/db_schema/temoa_schema_v3_1.sql
temoa/db_schema/temoa_schema_v4.sql
temoa/extensions/README.txt
temoa/extensions/__init__.py
temoa/extensions/get_comm_tech.py
temoa/extensions/breakeven/README.txt
temoa/extensions/breakeven/breakeven.py
temoa/extensions/method_of_morris/MM_README.md
temoa/extensions/method_of_morris/Method_of_Morris_README.txt
temoa/extensions/method_of_morris/__init__.py
temoa/extensions/method_of_morris/morris.py
temoa-4.0.0a1.dev20251201.dist-info/METADATA
temoa-4.0.0a1.dev20251201.dist-info/WHEEL
temoa-4.0.0a1.dev20251201.dist-info/entry_points.txt
temoa-4.0.0a1.dev20251201.dist-info/licenses/LICENSE.txt
temoa-4.0.0a1.dev20251201.dist-info/RECORD
