Metadata-Version: 2.4
Name: temoa
Version: 4.0.0a1.dev20251201
Summary: Tools for Energy Model Optimization and Analysis
Project-URL: Homepage, https://temoaproject.org
Project-URL: Documentation, https://temoaproject.github.io/temoa
Project-URL: Repository, https://github.com/TemoaProject/temoa
Author-email: TemoaProject Team <info@temoaproject.org>
License:                     GNU GENERAL PUBLIC LICENSE
License-File: LICENSE.txt
Requires-Python: >=3.12
Requires-Dist: deprecated>=1.2.14
Requires-Dist: graphviz>=0.20.3
Requires-Dist: highspy>=1.7.2
Requires-Dist: joblib
Requires-Dist: matplotlib==3.9.2
Requires-Dist: networkx>=3.3
Requires-Dist: numpy>=2.1.0
Requires-Dist: openpyxl>=3.1.5
Requires-Dist: pandas>=2.2.2
Requires-Dist: pint>=0.25.2
Requires-Dist: pyomo>=6.8.0
Requires-Dist: pytest>=8.3.2
Requires-Dist: rich>=14.2.0
Requires-Dist: salib>=1.5.1
Requires-Dist: scipy>=1.14.1
Requires-Dist: seaborn>=0.13.2
Requires-Dist: tabulate>=0.9.0
Requires-Dist: tomlkit>=0.12.0
Requires-Dist: typer>=0.20.0
Requires-Dist: xlsxwriter>=3.2.0
Provides-Extra: docs
Requires-Dist: myst-parser>=2.0.0; extra == 'docs'
Requires-Dist: sphinx-rtd-theme>=2.0.0; extra == 'docs'
Requires-Dist: sphinx>=7.4.7; extra == 'docs'
Requires-Dist: sphinxcontrib-bibtex>=2.6.2; extra == 'docs'
Requires-Dist: sphinxcontrib-htmlhelp>=2.1.0; extra == 'docs'
Requires-Dist: sphinxcontrib-serializinghtml>=2.0.0; extra == 'docs'
Provides-Extra: plotting
Requires-Dist: matplotlib>=3.9.2; extra == 'plotting'
Requires-Dist: seaborn>=0.13.2; extra == 'plotting'
Provides-Extra: solver
Requires-Dist: gurobipy<13,>=12.0.3; extra == 'solver'
